LICENSE
README.md
setup.py
pylerolero/__init__.py
pylerolero/pylerolero.py
pylerolero.egg-info/PKG-INFO
pylerolero.egg-info/SOURCES.txt
pylerolero.egg-info/dependency_links.txt
pylerolero.egg-info/top_level.txt