Metadata-Version: 2.1
Name: pylerolero
Version: 0.0.2
Summary: Gerador de lero-lero em formato de frases e textos.
Home-page: UNKNOWN
Author: João Marcos Campagnolo
Author-email: jota.campagnolo@gmail.com
License: MIT License
Project-URL: Bug Tracker, https://github.com/JotaCampagnolo/pylerolero/issues
Project-URL: Source Code, https://github.com/JotaCampagnolo/pylerolero
Keywords: fake lero frase texto
Platform: UNKNOWN
Requires-Python: >=3.10
License-File: LICENSE
